connectsrhft/__init__.py
connectsrhft/src/__init__.py
connectsrhft/src/connectsrhft.py
connectsrhft-0.0.14.dist-info/METADATA
connectsrhft-0.0.14.dist-info/WHEEL
connectsrhft-0.0.14.dist-info/top_level.txt
connectsrhft-0.0.14.dist-info/RECORD
