Metadata-Version: 2.1
Name: connectsrhft
Version: 0.0.14
Summary: Package to connect to SRHFT's API
Author: SRHFT
Classifier: Programming Language :: Python :: 3
Classifier: License :: OSI Approved :: MIT License
Classifier: Operating System :: OS Independent
Requires-Python: >=3.8
Requires-Dist: websocket-client ==1.6.1
Requires-Dist: requests
